python_neutronclient_ip_address_extension.py
setup.py
python_neutronclient_ip_address_extension.egg-info/PKG-INFO
python_neutronclient_ip_address_extension.egg-info/SOURCES.txt
python_neutronclient_ip_address_extension.egg-info/dependency_links.txt
python_neutronclient_ip_address_extension.egg-info/entry_points.txt
python_neutronclient_ip_address_extension.egg-info/pbr.json
python_neutronclient_ip_address_extension.egg-info/requires.txt
python_neutronclient_ip_address_extension.egg-info/top_level.txt