Metadata-Version: 1.1
Name: python-neutronclient-ip-address-extension
Version: 0.1
Summary: Rackspace IP Address Resource Extension for python-neutronclient
Home-page: http://github.com/rackerlabs/python_neutronclient_ip_address_extension
Author: Rackspace
Author-email: neutron-requests@lists.rackspace.com
License: Apache License, Version 2.0
Platform: UNKNOWN
Classifier: Development Status :: 5 - Production/Stable
Classifier: Environment :: Console
Classifier: Intended Audience :: Developers
Classifier: Intended Audience :: Information Technology
Classifier: License :: OSI Approved :: Apache Software License
Classifier: Operating System :: OS Independent
Classifier: Environment :: OpenStack
Classifier: Programming Language :: Python
